{
    "name": "Количество центральных крышек",
    "value": 0
}
{
    "name": "Количество оснований",
    "value": 0
}
{
    "name": "Количество боковых оснований",
    "value": 0
}
{
    "name": "Количество боковых крышек",
    "value": 0
}
{
    "name": "Количество соединительных профилей",
    "value": 0
}
{
    "name": "Количество рельс на складе",
    "value": 0
}
{
    "name": "Количество боковых крышек на двойные",
    "value": 0
}
{
    "name": "Количество клапанов AIR",
    "value": 0
}
{
    "name": "Количество клапанов VAC",
    "value": 0
}
{
    "name": "Количество клапанов CO2",
    "value": 0
}
{
    "name": "Количество клапанов O2",
    "value": 0
}
{
    "name": "Количество СИЗов",
    "value": 0
}